odoo/addons/account_avatax_exemption/README.rst
odoo/addons/account_avatax_exemption/__init__.py
odoo/addons/account_avatax_exemption/__manifest__.py
odoo/addons/account_avatax_exemption/controller/__init__.py
odoo/addons/account_avatax_exemption/controller/main.py
odoo/addons/account_avatax_exemption/data/cron.xml
odoo/addons/account_avatax_exemption/data/ir_sequence_data.xml
odoo/addons/account_avatax_exemption/data/queue.xml
odoo/addons/account_avatax_exemption/i18n/account_avatax_exemption.pot
odoo/addons/account_avatax_exemption/models/__init__.py
odoo/addons/account_avatax_exemption/models/avalara_salestax.py
odoo/addons/account_avatax_exemption/models/exemption.py
odoo/addons/account_avatax_exemption/models/product.py
odoo/addons/account_avatax_exemption/models/queue_job.py
odoo/addons/account_avatax_exemption/models/res_country_state.py
odoo/addons/account_avatax_exemption/readme/CONTRIBUTORS.rst
odoo/addons/account_avatax_exemption/readme/DESCRIPTION.rst
odoo/addons/account_avatax_exemption/readme/USAGE.rst
odoo/addons/account_avatax_exemption/security/ir.model.access.csv
odoo/addons/account_avatax_exemption/static/description/icon.png
odoo/addons/account_avatax_exemption/static/description/index.html
odoo/addons/account_avatax_exemption/static/description/menu_icon.png
odoo/addons/account_avatax_exemption/views/avalara_exemption_view.xml
odoo/addons/account_avatax_exemption/views/avalara_salestax_view.xml
odoo/addons/account_avatax_exemption/views/exemption_template_views.xml
odoo/addons/account_avatax_exemption/views/partner_view.xml
odoo/addons/account_avatax_exemption/views/product_view.xml
odoo/addons/account_avatax_exemption/views/res_country_state_view.xml
odoo/addons/account_avatax_exemption/views/website_exemption_form.xml
odoo/addons/account_avatax_exemption/views/website_exemption_tree.xml
odoo/addons/account_avatax_exemption/views/website_layout.xml
odoo14_addon_account_avatax_exemption-14.0.3.0.1.dist-info/METADATA
odoo14_addon_account_avatax_exemption-14.0.3.0.1.dist-info/WHEEL
odoo14_addon_account_avatax_exemption-14.0.3.0.1.dist-info/top_level.txt
odoo14_addon_account_avatax_exemption-14.0.3.0.1.dist-info/RECORD
