Metadata-Version: 2.1
Name: odoo14-addon-account-avatax-exemption
Version: 14.0.3.0.1
Summary: This application allows you to add exemptions to Avatax
Home-page: https://github.com/OCA/account-fiscal-rule
Author: Sodexis, Odoo Community Association (OCA)
Author-email: support@odoo-community.org
License: AGPL-3
Platform: UNKNOWN
Classifier: Programming Language :: Python
Classifier: Framework :: Odoo
Classifier: Framework :: Odoo :: 14.0
Classifier: License :: OSI Approved :: GNU Affero General Public License v3
Requires-Python: >=3.6
Requires-Dist: Avalara
Requires-Dist: odoo14-addon-account-avatax-exemption-base
Requires-Dist: odoo14-addon-account-avatax-sale-oca
Requires-Dist: odoo14-addon-queue-job
Requires-Dist: odoo <14.1dev,>=14.0a
